{
    "key": "group_63310abb5e173",
    "title": "Block: Timeline",
    "fields": [
        {
            "key": "field_6331fcacf4a82",
            "label": "Timeline Message",
            "name": "",
            "type": "message",
            "instructions": "",
            "required": 0,
            "conditional_logic": 0,
            "wrapper": {
                "width": "",
                "class": "",
                "id": ""
            },
            "message": "Please use preview mode to add Event blocks to this timeline.",
            "new_lines": "wpautop",
            "esc_html": 0
        }
    ],
    "location": [
        [
            {
                "param": "block",
                "operator": "==",
                "value": "rad\/timeline"
            }
        ]
    ],
    "menu_order": 0,
    "position": "normal",
    "style": "default",
    "label_placement": "top",
    "instruction_placement": "label",
    "hide_on_screen": "",
    "active": true,
    "description": "",
    "show_in_rest": 0,
    "modified": 1664220372
}